{"features": ["Bluetooth", "4WD/AWD", "Android Auto", "Apple CarPlay", "Keyless Ignition System", "Wi-Fi Hotspot", "Automatic High Beams", "Lane Departure Warning", "Lane Keep Assist", "Sunroof/Moonroof", "Wireless Phone Charging", "Blind Spot Monitor", "Forward Collision Warning", "Navigation System", "Parking Assistance", "Automatic Climate Control", "Turbo Charged Engine", "Cruise Control"], "information": {"Body Style": "Crew Cab", "Exterior Color": "Summit White", "Interior Color": "Jet Black/Graystone, Perforated Leather Seating Surfaces", "Engine": "3.0L Duramax<sup>&reg;</sup> Turbo Diesel engine", "Transmission": "Automatic / 4WD", "VIN": "3GCUDHE88RG144827"}, "price": "$72,140", "name": "2024__Chevrolet_Silverado_1500", "link": "https://www.pinkertonlynchburg.com/new-Lynchburg-2024-Chevrolet-Silverado+1500-ZR2-3GCUDHE88RG144827"}